rlane_tivo-1.0.5.dist-info/METADATA
rlane_tivo-1.0.5.dist-info/WHEEL
rlane_tivo-1.0.5.dist-info/entry_points.txt
rlane_tivo-1.0.5.dist-info/licenses/LICENSE
tivo/__init__.py
tivo/__main__.py
tivo/cli.py
tivo/cmd.py
tivo/commands/__init__.py
tivo/commands/downch.py
tivo/commands/emulator.py
tivo/commands/getch.py
tivo/commands/list.py
tivo/commands/setch.py
tivo/commands/upch.py
tivo/core.py
tivo/device.py
tivo/remote.py
tivo/ui.py
rlane_tivo-1.0.5.dist-info/RECORD
