Metadata-Version: 2.1
Name: rlane-tivo
Version: 1.0.5
Summary: A curses-based TiVo remote control
Keywords: curses,home-automation,python,tivo
Author-Email: Russel Lane <russel@rlane.com>
License: MIT
Classifier: Development Status :: 4 - Beta
Classifier: Intended Audience :: End Users/Desktop
Classifier: License :: OSI Approved :: MIT License
Classifier: Programming Language :: Python :: 3
Classifier: Topic :: Home Automation
Project-URL: Homepage, https://github.com/russellane/tivo
Requires-Python: >=3.10
Requires-Dist: loguru>=0.7.2
Requires-Dist: rlane-libcli>=1.0.8
Requires-Dist: rlane-libcurses>=1.0.9
